README.md
setup.py
sofos/__init__.py
sofos/database.py
sofos/dbf.py
sofos/dbf2.py
sofos/gr.py
sofos/report.py
sofos/report_table.py
sofos.egg-info/PKG-INFO
sofos.egg-info/SOURCES.txt
sofos.egg-info/dependency_links.txt
sofos.egg-info/requires.txt
sofos.egg-info/top_level.txt
sofos/bin/sofos-project
sofos/models/__init__.py
sofos/models/booleanfield.py
sofos/models/charfield.py
sofos/models/charnumfield.py
sofos/models/dateemptyfield.py
sofos/models/datefield.py
sofos/models/decimalfield.py
sofos/models/field.py
sofos/models/foreignkey.py
sofos/models/integerfield.py
sofos/models/model.py
sofos/models/textfield.py
sofos/models/weekdaysfield.py
sofos/qt/__init__.py
sofos/qt/abstract_form.py
sofos/qt/fautoform.py
sofos/qt/fautoformtable.py
sofos/qt/fautoformtablefound.py
sofos/qt/fautoformtablewidget.py
sofos/qt/ffindform.py
sofos/qt/fmasterdetail.py
sofos/qt/settings.py
sofos/qt/tcheckbox.py
sofos/qt/tcombo.py
sofos/qt/tcombodb.py
sofos/qt/tdate.py
sofos/qt/tdateempty.py
sofos/qt/tintegerspin.py
sofos/qt/tnumeric.py
sofos/qt/tnumericspin.py
sofos/qt/translations.py
sofos/qt/ttext.py
sofos/qt/ttextbutton.py
sofos/qt/ttextline.py
sofos/qt/tweekdays.old.py
sofos/qt/tweekdays.py
sofos/qt/tyesnocombo.py
sofos/qt/vsortwidgetitem.py
sofos/qt/widget_selector.py
sofos/templates/_validators.py
sofos/templates/forms.py
sofos/templates/init_db.sql
sofos/templates/main.py
sofos/templates/main.qrc
sofos/templates/main_rc.py
sofos/templates/manage.py
sofos/templates/master-detail.py
sofos/templates/mdi_child.py
sofos/templates/models.py
sofos/templates/readme.txt
sofos/templates/settings.py
sofos/templates/images/app.png
sofos/templates/images/copy.png
sofos/templates/images/cut.png
sofos/templates/images/new.png
sofos/templates/images/open.png
sofos/templates/images/paste.png
sofos/templates/images/save.png
sofos/templates/zforms/__init__.py
sofos/templates/zforms/template_custom_form.py