Metadata-Version: 1.1
Name: sofos
Version: 0.9.7
Summary: Gui Database Applications Generator
Home-page: https://github.com/tedlaz/sofos
Author: Ted Lazaros
Author-email: tedlaz@gmail.com
License: GPLv3
Keywords: database,gui,pyqt5
Platform: UNKNOWN
Classifier: Development Status :: 4 - Beta
Classifier: Environment :: Console
Classifier: Environment :: X11 Applications :: Qt
Classifier: Environment :: Win32 (MS Windows)
Classifier: Intended Audience :: Developers
Classifier: Natural Language :: English
Classifier: Operating System :: OS Independent
Classifier: Programming Language :: Python
Classifier: Programming Language :: Python :: 3
Classifier: Programming Language :: Python :: 3 :: Only
Classifier: Programming Language :: Python :: 3.5
Classifier: Programming Language :: Python :: 3.6
Classifier: Topic :: Software Development :: Build Tools
